Metadata-Version: 1.0
Name: anusha
Version: 0.1
Summary: Gaussian and binomialdistributions
Home-page: UNKNOWN
Author: Anusha Devulapally
Author-email: anushadevulapally2013@gmail.com
License: UNKNOWN
Platform: UNKNOWN
